[[{"__type__":"cc.Prefab","_name":"people","data":{"__id__":1}},{"__type__":"cc.Node","_name":"people","_level":1,"_components":[{"__type__":"cc.Sprite","node":{"__id__":1},"_materials":[{"__uuid__":"ecpdLyjvZBwrvm+cedCcQy"}],"_spriteFrame":{"__uuid__":"69Y8GHj9JCWZlPQf3Obr6x"},"_sizeMode":2},{"__type__":"05cf0dFq/ZLGqi85cEvcSy2","node":{"__id__":1}},{"__type__":"cc.RigidBody","node":{"__id__":1},"enabledContactListener":true,"awakeOnLoad":false},{"__type__":"cc.PhysicsBoxCollider","node":{"__id__":1},"_density":0,"_sensor":true,"_friction":0,"_offset":{"__type__":"cc.Vec2","y":-24},"_size":{"__type__":"cc.Size","width":21,"height":48}}],"_prefab":{"__type__":"cc.PrefabInfo","root":{"__id__":1},"asset":{"__uuid__":"20Ia9OjHdIoY1fPjoNbx34"},"fileId":"16UM/HbVlKGaG7v+hUFRbG"},"_contentSize":{"__type__":"cc.Size","width":21,"height":48},"_anchorPoint":{"__type__":"cc.Vec2","x":0.5,"y":1}}],{"__type__":"cc.SpriteFrame","content":{"name":"people1","texture":"d5uLKPRwhKNr9hcbuKBCwt","rect":[0,0,21,48],"offset":[0,0],"originalSize":[21,48],"capInsets":[0,0,0,0]}}]